alibabacloud_oss20190517/__init__.py
alibabacloud_oss20190517/client.py
alibabacloud_oss20190517/models.py
alibabacloud_oss20190517-1.0.6.dist-info/LICENSE
alibabacloud_oss20190517-1.0.6.dist-info/METADATA
alibabacloud_oss20190517-1.0.6.dist-info/WHEEL
alibabacloud_oss20190517-1.0.6.dist-info/top_level.txt
alibabacloud_oss20190517-1.0.6.dist-info/RECORD
